micropython_pca9685/__init__.py
micropython_pca9685/i2c_helpers.py
micropython_pca9685/motor.py
micropython_pca9685/pca9685.py
micropython_pca9685-0.1.0.dist-info/LICENSE
micropython_pca9685-0.1.0.dist-info/METADATA
micropython_pca9685-0.1.0.dist-info/WHEEL
micropython_pca9685-0.1.0.dist-info/top_level.txt
micropython_pca9685-0.1.0.dist-info/RECORD
