Metadata-Version: 2.1
Name: micropython-pca9685
Version: 0.1.0
Summary: MicroPython Driver for the PCA9685
Author-email: JDM <xxyx@mailmeto.mozmail.com>
License: MIT
Project-URL: Homepage, https://github.com/jposada202020/MicroPython_PCA9685
Keywords: sensor,micropython,pca9685,micropython,driver,pca9685
Classifier: Intended Audience :: Developers
Classifier: Topic :: Software Development :: Libraries
Classifier: Topic :: Software Development :: Embedded Systems
Classifier: Topic :: System :: Hardware
Classifier: License :: OSI Approved :: MIT License
Classifier: Programming Language :: Python :: Implementation :: MicroPython
License-File: LICENSE
